[
  {
    "label": "How many kinks of design patterns are there in Java?",
    "answer": "23"
  },
  {
    "label": "Which year was Ruby born on?",
    "answer": "1995"
  },
  {
    "label": "What is the next major version number of Angular after Angular2?",
    "answer": "4"
  },
  {
    "label": "What is the largest value of INT32?",
    "answer": "2147483647"
  },
  {
    "label": "What is the next major version number of React after React 0.14?",
    "answer": "15"
  },
  {
    "label": "How many weeks did Linus spend on creating Git?",
    "answer": "2"
  }
]